vebits_api/__init__.py
vebits_api/bbox_util.py
vebits_api/detector_util.py
vebits_api/detector_utils.py
vebits_api/im_util.py
vebits_api/labelmap_util.py
vebits_api/others_util.py
vebits_api/string_int_label_map_pb2.py
vebits_api/vis_util.py
vebits_api/xml_util.py
vebits_api-1.1.5.dist-info/LICENSE
vebits_api-1.1.5.dist-info/METADATA
vebits_api-1.1.5.dist-info/WHEEL
vebits_api-1.1.5.dist-info/top_level.txt
vebits_api-1.1.5.dist-info/RECORD
